airless/slack/__init__.py
airless/slack/hook/__init__.py
airless/slack/hook/slack.py
airless/slack/operator/__init__.py
airless/slack/operator/google.py
airless/slack/operator/slack.py
airless_slack-0.3.0.dist-info/METADATA
airless_slack-0.3.0.dist-info/WHEEL
airless_slack-0.3.0.dist-info/top_level.txt
airless_slack-0.3.0.dist-info/RECORD
