Metadata-Version: 2.4
Name: airless-slack
Version: 0.3.0
Summary: Airless package to manage slack
License: MIT License
Project-URL: Homepage, https://github.com/astercapital/airless
Project-URL: Bug Tracker, https://github.com/astercapital/airless/issues
Requires-Python: >=3.9
Requires-Dist: airless-core>=0.2.1
Requires-Dist: airless-google-cloud-core>=0.1.0
Requires-Dist: airless-google-cloud-secret-manager>=0.1.0
